comic_text_detector/LICENSE
comic_text_detector/__init__.py
comic_text_detector/basemodel.py
comic_text_detector/db_dataset.py
comic_text_detector/inference.py
comic_text_detector/seg_dataset.py
comic_text_detector/text_rendering.py
comic_text_detector/train_db.py
comic_text_detector/train_seg.py
comic_text_detector/models/__init__.py
comic_text_detector/models/yolov5/__init__.py
comic_text_detector/models/yolov5/common.py
comic_text_detector/models/yolov5/yolo.py
comic_text_detector/utils/__init__.py
comic_text_detector/utils/db_utils.py
comic_text_detector/utils/export.py
comic_text_detector/utils/general.py
comic_text_detector/utils/imgproc_utils.py
comic_text_detector/utils/io_utils.py
comic_text_detector/utils/loss.py
comic_text_detector/utils/textblock.py
comic_text_detector/utils/textmask.py
comic_text_detector/utils/weight_init.py
comic_text_detector/utils/yolov5_utils.py
owocr/__init__.py
owocr/__main__.py
owocr/config.py
owocr/ocr.py
owocr/run.py
owocr/screen_coordinate_picker.py
owocr/lens_protos/aim_communication_pb2.py
owocr/lens_protos/aim_query_pb2.py
owocr/lens_protos/lens_overlay_client_context_pb2.py
owocr/lens_protos/lens_overlay_client_logs_pb2.py
owocr/lens_protos/lens_overlay_client_platform_pb2.py
owocr/lens_protos/lens_overlay_cluster_info_pb2.py
owocr/lens_protos/lens_overlay_contextual_inputs_pb2.py
owocr/lens_protos/lens_overlay_deep_gleam_data_pb2.py
owocr/lens_protos/lens_overlay_document_pb2.py
owocr/lens_protos/lens_overlay_filters_pb2.py
owocr/lens_protos/lens_overlay_geometry_pb2.py
owocr/lens_protos/lens_overlay_image_crop_pb2.py
owocr/lens_protos/lens_overlay_image_data_pb2.py
owocr/lens_protos/lens_overlay_interaction_request_metadata_pb2.py
owocr/lens_protos/lens_overlay_knowledge_intent_query_pb2.py
owocr/lens_protos/lens_overlay_knowledge_query_pb2.py
owocr/lens_protos/lens_overlay_math_solver_query_pb2.py
owocr/lens_protos/lens_overlay_message_set_pb2.py
owocr/lens_protos/lens_overlay_overlay_object_pb2.py
owocr-1.21.6.dist-info/licenses/LICENSE
owocr-1.21.6.dist-info/METADATA
owocr-1.21.6.dist-info/WHEEL
owocr-1.21.6.dist-info/entry_points.txt
owocr-1.21.6.dist-info/top_level.txt
owocr-1.21.6.dist-info/RECORD
