Metadata-Version: 2.4
Name: owocr
Version: 1.21.6
Summary: Japanese OCR
Author-email: AuroraWright <fallingluma@gmail.com>
License-Expression: GPL-3.0-only
Project-URL: Homepage, https://github.com/AuroraWright/owocr
Classifier: Programming Language :: Python :: 3
Requires-Python: >=3.11
License-File: LICENSE
Requires-Dist: jaconv
Requires-Dist: loguru
Requires-Dist: numpy
Requires-Dist: Pillow>=10.0.0
Requires-Dist: pynput<=1.7.8
Requires-Dist: websockets>=14.0
Requires-Dist: desktop-notifier>=6.1.0
Requires-Dist: mss>=10.1.0
Requires-Dist: psutil
Requires-Dist: curl_cffi
Requires-Dist: pywin32; platform_system == "Windows"
Requires-Dist: pyobjc; platform_system == "Darwin"
Requires-Dist: pyperclipfix; platform_system == "Linux"
Provides-Extra: faster-png
Requires-Dist: fpng-py; extra == "faster-png"
Provides-Extra: easyocr
Requires-Dist: easyocr; extra == "easyocr"
Provides-Extra: rapidocr
Requires-Dist: rapidocr>=3.4.0; extra == "rapidocr"
Requires-Dist: onnxruntime; extra == "rapidocr"
Provides-Extra: meikiocr
Requires-Dist: meikiocr>=0.1.4; extra == "meikiocr"
Provides-Extra: mangaocr
Requires-Dist: manga-ocr; extra == "mangaocr"
Requires-Dist: setuptools<80; extra == "mangaocr"
Requires-Dist: scipy; extra == "mangaocr"
Requires-Dist: pyclipper; extra == "mangaocr"
Requires-Dist: torchvision; extra == "mangaocr"
Requires-Dist: torch-summary; extra == "mangaocr"
Requires-Dist: opencv-python; extra == "mangaocr"
Requires-Dist: shapely; extra == "mangaocr"
Provides-Extra: winocr
Requires-Dist: winocr; extra == "winocr"
Provides-Extra: oneocr
Requires-Dist: oneocr>=1.0.9; extra == "oneocr"
Provides-Extra: lens
Requires-Dist: protobuf>=6.33.2; extra == "lens"
Provides-Extra: gvision
Requires-Dist: google-cloud-vision; extra == "gvision"
Provides-Extra: azure
Requires-Dist: azure-ai-vision-imageanalysis; extra == "azure"
Dynamic: license-file
